opustrainer/__init__.py
opustrainer/__main__.py
opustrainer/alignments.py
opustrainer/logger.py
opustrainer/shuffle.py
opustrainer/tokenizers.py
opustrainer/trainer.py
opustrainer/types.py
opustrainer/modifiers/__init__.py
opustrainer/modifiers/merge.py
opustrainer/modifiers/noise.py
opustrainer/modifiers/placeholders.py
opustrainer/modifiers/pool.py
opustrainer/modifiers/prefix.py
opustrainer/modifiers/punctuation.py
opustrainer/modifiers/retokenize.py
opustrainer/modifiers/surface.py
opustrainer/modifiers/typos.py
opustrainer-0.5.dist-info/licenses/LICENSE
opustrainer-0.5.dist-info/METADATA
opustrainer-0.5.dist-info/WHEEL
opustrainer-0.5.dist-info/entry_points.txt
opustrainer-0.5.dist-info/top_level.txt
opustrainer-0.5.dist-info/RECORD
