Metadata-Version: 2.4
Name: opustrainer
Version: 0.5
Summary: Scheduled training for machine translation systems
Author-email: Jelmer van der Linde <jelmer.vanderlinde@ed.ac.uk>, Nikolay Bogoychev <n.bogoych@ed.ac.uk>
Project-URL: Homepage, https://github.com/hplt-project/OpusTrainer
Project-URL: Bug Tracker, https://github.com/hplt-project/OpusTrainer/issues
Classifier: Programming Language :: Python :: 3
Classifier: License :: OSI Approved :: MIT License
Classifier: Operating System :: OS Independent
Classifier: Development Status :: 4 - Beta
Classifier: Environment :: Console
Classifier: Intended Audience :: Science/Research
Classifier: Topic :: Scientific/Engineering
Requires-Python: >=3.8
License-File: LICENSE
Requires-Dist: PyYAML>=6.0.1
Requires-Dist: sacremoses>=0.1.0
Requires-Dist: sentencepiece==0.1.99
Requires-Dist: typo==0.1.5
Provides-Extra: test
Requires-Dist: parameterized==0.9.0; extra == "test"
Dynamic: license-file
